LICENSE
README.md
setup.py
irff/AtomDance.py
irff/LearningMachine.py
irff/RadiusCutOff.py
irff/__init__.py
irff/dingtalk.py
irff/emdk.py
irff/getNeighbor.c
irff/getNeighbor.pyx
irff/getNeighbors.py
irff/intCheck.py
irff/irff.py
irff/irff_autograd.py
irff/irff_np.py
irff/link.py
irff/mlqeq.py
irff/molecule.py
irff/mpnn.py
irff/neighbor.c
irff/neighbor.pyx
irff/neighbors.py
irff/qeq.py
irff/reax.py
irff/reax_data.py
irff/reax_force_data.py
irff/reax_nn.py
irff/reaxff_jax.py
irff/reaxff_torch.py
irff/reaxfflib.py
irff/set_matrix_tensor.py
irff/spectra.py
irff/trainer.py
irff/zmatrix.py
irff.egg-info/PKG-INFO
irff.egg-info/SOURCES.txt
irff.egg-info/dependency_links.txt
irff.egg-info/top_level.txt
irff/data/ColData.py
irff/data/__init__.py
irff/data/dpdata.py
irff/data/mdtodata.py
irff/data/prep_data.py
irff/data/qeout_to_traj.py
irff/deb/__init__.py
irff/deb/compare_energies.py
irff/deb/deb_bde.py
irff/deb/hbdeb.py
irff/deb/ird.py
irff/deb/irdeb.py
irff/deb/irffdeb.py
irff/deb/irnan.py
irff/deb/mpdeb.py
irff/deb/reax_debug.py
irff/deb/reax_gulp.py
irff/deb/theta.py
irff/dft/CheckEmol.py
irff/dft/SinglePointEnergy.py
irff/dft/__init__.py
irff/dft/cpmd.py
irff/dft/dftb.py
irff/dft/nwchem.py
irff/dft/qe.py
irff/dft/siesta.py
irff/dft/siesta_zmatix_constrain.py
irff/dft/smd_server.py
irff/md/ReactionCapture.py
irff/md/__init__.py
irff/md/gofr.py
irff/md/gulp.py
irff/md/hugoniot.py
irff/md/irmd.py
irff/md/lammps.py
irff/ml/__init__.py
irff/ml/data.py
irff/ml/evaluate_data.py
irff/ml/evolution.py
irff/ml/ffield.py
irff/ml/fit.py
irff/ml/fluctuation.py
irff/ml/gaqeq.py
irff/ml/genetic.py
irff/ml/gpfit_tfv2.py
irff/ml/harmonic.py
irff/ml/nn.py
irff/ml/reax_funcs.py
irff/ml/train.py
irff/plot/BondEnergy.py
irff/plot/CheckAng.py
irff/plot/LearningResults.py
irff/plot/LearningResultsAng.py
irff/plot/MessagePassing.py
irff/plot/__init__.py
irff/plot/abc.py
irff/plot/angel_to_bond.py
irff/plot/bde.py
irff/plot/compare_energies.py
irff/plot/fingerprint.py
irff/plot/gofr.py
irff/plot/irnn_plot.py
irff/plot/label_md.py
irff/plot/labels.py
irff/plot/morse.py
irff/plot/morse_taper.py
