Metadata-Version: 2.1
Name: irff
Version: 1.7.6
Summary: Intelligent Reactive Force Field
Home-page: https://gitee.com/fenggo/I-ReaxFF
Download-URL: https://gitee.com/fenggo/I-ReaxFF/archive/1.7.6.tar.gz
Author: FengGo
Author-email: fengguo@lcu.edu.cn
License: LGPL
License-File: LICENSE
